{"is_source_file": false, "format": "", "description": "", "external_files": [], "external_methods": [], "published": [], "classes": [], "methods": [], "calls": [], "search-terms": [], "state": 2, "file_id": 23, "knowledge_revision": 49, "git_revision": "06043db9a3f2fcd5e4f53a23899491cdf289a557", "hash": "339d6918efd3c400b9fc373cef4b4d48", "format-version": 4, "code-base-name": "frontend_react", "filename": "frontend_react/src/App.css", "revision_history": [{"49": "06043db9a3f2fcd5e4f53a23899491cdf289a557"}]}